[
    {
        "adult": false,
        "backdrop_path": "/4DimUX9TgImWdMXPyL6n9nyTZkG.jpg",
        "genre_ids": [
            18
        ],
        "id": 1567953,
        "original_language": "zh",
        "original_title": "芳草碧連天",
        "overview": "",
        "popularity": 0.0143,
        "poster_path": "/AfVQf8iOXmfZn5TuDEOvZI50kkk.jpg",
        "release_date": "2025-10-27",
        "title": "芳草碧連天",
        "video": false,
        "vote_average": 0.0,
        "vote_count": 0,
        "genre_ids_zh": [
            "剧情"
        ],
        "original_language_zh": "汉语"
    },
    {
        "adult": false,
        "backdrop_path": "/eFEQuUhDJAI0m39xnTfj4jPnbXt.jpg",
        "genre_ids": [
            16,
            18
        ],
        "id": 1567983,
        "original_language": "zh",
        "original_title": "眼淚的果實",
        "overview": "",
        "popularity": 0.0143,
        "poster_path": "/qpFzDnSR2M17IwCDjgEiEpcJ3zL.jpg",
        "release_date": "2025-10-27",
        "title": "眼淚的果實",
        "video": false,
        "vote_average": 0.0,
        "vote_count": 0,
        "genre_ids_zh": [
            "动画",
            "剧情"
        ],
        "original_language_zh": "汉语"
    },
    {
        "adult": false,
        "backdrop_path": "/6hYwAshJzVKY5vMeT2nXi0wRrpe.jpg",
        "genre_ids": [],
        "id": 1568563,
        "original_language": "zh",
        "original_title": "後殖民皇后",
        "overview": "",
        "popularity": 0.0071,
        "poster_path": "/51s6a5RC4tdVysRc2j16eWPMjNz.jpg",
        "release_date": "2025-10-27",
        "title": "後殖民皇后",
        "video": false,
        "vote_average": 0.0,
        "vote_count": 0,
        "genre_ids_zh": [],
        "original_language_zh": "汉语"
    },
    {
        "adult": false,
        "backdrop_path": null,
        "genre_ids": [
            18
        ],
        "id": 1451676,
        "original_language": "en",
        "original_title": "THE REAL DEAL",
        "overview": "",
        "popularity": 1.1712,
        "poster_path": "/4nYX53MNB1sDRwK6P1HIU2lZeLe.jpg",
        "release_date": "2025-10-27",
        "title": "THE REAL DEAL",
        "video": false,
        "vote_average": 0.0,
        "vote_count": 0,
        "genre_ids_zh": [
            "剧情"
        ],
        "original_language_zh": "英语"
    },
    {
        "adult": false,
        "backdrop_path": "/89eOJ5qnVvhVJFqKzD11ALR1TBV.jpg",
        "genre_ids": [
            99
        ],
        "id": 1561278,
        "original_language": "en",
        "original_title": "Weaving Anni Albers",
        "overview": "",
        "popularity": 0.3321,
        "poster_path": "/bwlNqvokDKyYFRI6jluCEQ82Ji3.jpg",
        "release_date": "2025-10-27",
        "title": "Weaving Anni Albers",
        "video": false,
        "vote_average": 0.0,
        "vote_count": 0,
        "genre_ids_zh": [
            "纪录"
        ],
        "original_language_zh": "英语"
    },
    {
        "adult": false,
        "backdrop_path": null,
        "genre_ids": [
            99,
            36
        ],
        "id": 1553866,
        "original_language": "en",
        "original_title": "Kissinger",
        "overview": "",
        "popularity": 0.3932,
        "poster_path": null,
        "release_date": "2025-10-27",
        "title": "Kissinger",
        "video": false,
        "vote_average": 0.0,
        "vote_count": 0,
        "genre_ids_zh": [
            "纪录",
            "历史"
        ],
        "original_language_zh": "英语"
    },
    {
        "adult": false,
        "backdrop_path": null,
        "genre_ids": [
            99
        ],
        "id": 883101,
        "original_language": "en",
        "original_title": "The Woman Who Poked the Leopard",
        "overview": "",
        "popularity": 0.2321,
        "poster_path": "/tF7dVc4md2w8RUzXlSpZP45tf5j.jpg",
        "release_date": "2025-10-27",
        "title": "The Woman Who Poked the Leopard",
        "video": false,
        "vote_average": 0.0,
        "vote_count": 0,
        "genre_ids_zh": [
            "纪录"
        ],
        "original_language_zh": "英语"
    },
    {
        "adult": false,
        "backdrop_path": null,
        "genre_ids": [
            35
        ],
        "id": 1559613,
        "original_language": "en",
        "original_title": "Mo Amer: Wild World",
        "overview": "",
        "popularity": 0.2221,
        "poster_path": null,
        "release_date": "2025-10-27",
        "title": "Mo Amer: Wild World",
        "video": false,
        "vote_average": 0.0,
        "vote_count": 0,
        "genre_ids_zh": [
            "喜剧"
        ],
        "original_language_zh": "英语"
    },
    {
        "adult": false,
        "backdrop_path": null,
        "genre_ids": [
            18
        ],
        "id": 1563845,
        "original_language": "en",
        "original_title": "Shards of Us",
        "overview": "",
        "popularity": 0.0518,
        "poster_path": "/p7HoYM8P5xArE0gTizLCLV52USF.jpg",
        "release_date": "2025-10-27",
        "title": "Shards of Us",
        "video": false,
        "vote_average": 0.0,
        "vote_count": 0,
        "genre_ids_zh": [
            "剧情"
        ],
        "original_language_zh": "英语"
    },
    {
        "adult": false,
        "backdrop_path": null,
        "genre_ids": [],
        "id": 1545042,
        "original_language": "en",
        "original_title": "Boogie",
        "overview": "",
        "popularity": 0.3574,
        "poster_path": null,
        "release_date": "2025-10-27",
        "title": "Boogie",
        "video": false,
        "vote_average": 0.0,
        "vote_count": 0,
        "genre_ids_zh": [],
        "original_language_zh": "英语"
    },
    {
        "adult": false,
        "backdrop_path": null,
        "genre_ids": [
            18
        ],
        "id": 1456356,
        "original_language": "en",
        "original_title": "One Way Ticket to Tbilisi",
        "overview": "",
        "popularity": 0.2197,
        "poster_path": "/qXZ4cVbydyOnFDMvH2jnPSv96kL.jpg",
        "release_date": "2025-10-27",
        "title": "One Way Ticket to Tbilisi",
        "video": false,
        "vote_average": 0.0,
        "vote_count": 0,
        "genre_ids_zh": [
            "剧情"
        ],
        "original_language_zh": "英语"
    },
    {
        "adult": false,
        "backdrop_path": null,
        "genre_ids": [
            18
        ],
        "id": 1563838,
        "original_language": "en",
        "original_title": "ZAZA",
        "overview": "",
        "popularity": 0.0492,
        "poster_path": null,
        "release_date": "2025-10-27",
        "title": "ZAZA",
        "video": false,
        "vote_average": 0.0,
        "vote_count": 0,
        "genre_ids_zh": [
            "剧情"
        ],
        "original_language_zh": "英语"
    },
    {
        "adult": false,
        "backdrop_path": null,
        "genre_ids": [
            18
        ],
        "id": 1563882,
        "original_language": "en",
        "original_title": "Paravan",
        "overview": "",
        "popularity": 0.0538,
        "poster_path": "/pIItFTryg5hVk5W4NVAaizJXiTI.jpg",
        "release_date": "2025-10-27",
        "title": "Paravan",
        "video": false,
        "vote_average": 0.0,
        "vote_count": 0,
        "genre_ids_zh": [
            "剧情"
        ],
        "original_language_zh": "英语"
    },
    {
        "adult": false,
        "backdrop_path": null,
        "genre_ids": [
            35
        ],
        "id": 1563841,
        "original_language": "en",
        "original_title": "National Treasures",
        "overview": "",
        "popularity": 0.0512,
        "poster_path": "/9s7ZXBUE8gF038tsWXulDjiTsbI.jpg",
        "release_date": "2025-10-27",
        "title": "National Treasures",
        "video": false,
        "vote_average": 0.0,
        "vote_count": 0,
        "genre_ids_zh": [
            "喜剧"
        ],
        "original_language_zh": "英语"
    },
    {
        "adult": false,
        "backdrop_path": null,
        "genre_ids": [
            35
        ],
        "id": 1561242,
        "original_language": "en",
        "original_title": "Shutter",
        "overview": "",
        "popularity": 0.0669,
        "poster_path": "/16rdEOFIb5UuNaxVN46XwB2Xa3j.jpg",
        "release_date": "2025-10-27",
        "title": "Shutter",
        "video": false,
        "vote_average": 0.0,
        "vote_count": 0,
        "genre_ids_zh": [
            "喜剧"
        ],
        "original_language_zh": "英语"
    },
    {
        "adult": false,
        "backdrop_path": null,
        "genre_ids": [
            35
        ],
        "id": 1563887,
        "original_language": "en",
        "original_title": "The Most Powerful Human on Earth",
        "overview": "",
        "popularity": 0.0718,
        "poster_path": "/BzavEQy51Skr1NUuMcFePtlUXJ.jpg",
        "release_date": "2025-10-27",
        "title": "The Most Powerful Human on Earth",
        "video": false,
        "vote_average": 0.0,
        "vote_count": 0,
        "genre_ids_zh": [
            "喜剧"
        ],
        "original_language_zh": "英语"
    },
    {
        "adult": false,
        "backdrop_path": null,
        "genre_ids": [],
        "id": 1566503,
        "original_language": "en",
        "original_title": "Two Futures",
        "overview": "",
        "popularity": 0.0214,
        "poster_path": "/xbFz6ua4TIKoLg7nc5CdfmLnpcl.jpg",
        "release_date": "2025-10-27",
        "title": "Two Futures",
        "video": false,
        "vote_average": 0.0,
        "vote_count": 0,
        "genre_ids_zh": [],
        "original_language_zh": "英语"
    },
    {
        "adult": false,
        "backdrop_path": "/7zfy73kcdEOPjmA2olTaOrBnHTM.jpg",
        "genre_ids": [
            99
        ],
        "id": 1568372,
        "original_language": "en",
        "original_title": "Midnight in the War Room",
        "overview": "",
        "popularity": 0.0071,
        "poster_path": "/26yj9KWDdViGgpUgECrEC1XykJb.jpg",
        "release_date": "2025-10-27",
        "title": "Midnight in the War Room",
        "video": false,
        "vote_average": 0.0,
        "vote_count": 0,
        "genre_ids_zh": [
            "纪录"
        ],
        "original_language_zh": "英语"
    },
    {
        "adult": false,
        "backdrop_path": "/kq4RMwOhoZzzi7Jsefnz0boLocD.jpg",
        "genre_ids": [
            18,
            27,
            14
        ],
        "id": 1568579,
        "original_language": "en",
        "original_title": "Remnants",
        "overview": "",
        "popularity": 0.0071,
        "poster_path": "/9tj8tlzWYJ2tiHdRJAOpihZcy3A.jpg",
        "release_date": "2025-10-27",
        "title": "Remnants",
        "video": false,
        "vote_average": 0.0,
        "vote_count": 0,
        "genre_ids_zh": [
            "剧情",
            "恐怖",
            "奇幻"
        ],
        "original_language_zh": "英语"
    },
    {
        "adult": false,
        "backdrop_path": "/dkK5A1NMWccOXDu97tpgFMofAdW.jpg",
        "genre_ids": [
            28
        ],
        "id": 1566155,
        "original_language": "fr",
        "original_title": "Star Wars 10Kâtre",
        "overview": "",
        "popularity": 0.3701,
        "poster_path": "/hge4Y26wcG3xJDJlLsPC29fqauW.jpg",
        "release_date": "2025-10-27",
        "title": "Star Wars 10Kâtre",
        "video": false,
        "vote_average": 0.0,
        "vote_count": 0,
        "genre_ids_zh": [
            "动作"
        ],
        "original_language_zh": "法语"
    },
    {
        "adult": false,
        "backdrop_path": "/gpHOJ1yj1LTYB0wOGWrr5DnhT1A.jpg",
        "genre_ids": [],
        "id": 1566838,
        "original_language": "es",
        "original_title": "31 Minutos: Bodoque contra el metano",
        "overview": "",
        "popularity": 0.1527,
        "poster_path": "/bsGWeuXnvZTObYpzly6LTFQcNfv.jpg",
        "release_date": "2025-10-27",
        "title": "31 Minutos: Bodoque contra el metano",
        "video": false,
        "vote_average": 0.0,
        "vote_count": 0,
        "genre_ids_zh": [],
        "original_language_zh": "西班牙语"
    },
    {
        "adult": false,
        "backdrop_path": "/lMuN5nUboesQ9JR39JC2bHHLBzc.jpg",
        "genre_ids": [],
        "id": 1562214,
        "original_language": "es",
        "original_title": "El beso de la muerte",
        "overview": "",
        "popularity": 0.0678,
        "poster_path": "/zlK5by9UBGcW6UZixEUNJJA3zne.jpg",
        "release_date": "2025-10-27",
        "title": "El beso de la muerte",
        "video": false,
        "vote_average": 0.0,
        "vote_count": 0,
        "genre_ids_zh": [],
        "original_language_zh": "西班牙语"
    },
    {
        "adult": false,
        "backdrop_path": null,
        "genre_ids": [
            18
        ],
        "id": 1264169,
        "original_language": "pt",
        "original_title": "Criadas",
        "overview": "",
        "popularity": 0.8296,
        "poster_path": "/95UFL6vqF9owZwqZhkZTqupKXcV.jpg",
        "release_date": "2025-10-27",
        "title": "Criadas",
        "video": false,
        "vote_average": 0.0,
        "vote_count": 0,
        "genre_ids_zh": [
            "剧情"
        ],
        "original_language_zh": "葡萄牙语"
    },
    {
        "adult": false,
        "backdrop_path": null,
        "genre_ids": [
            99
        ],
        "id": 1565473,
        "original_language": "pt",
        "original_title": "Alma Errante – Hibakusha",
        "overview": "",
        "popularity": 0.2752,
        "poster_path": "/yg6YnbBHO9EiZS9H4S9khfXSnYZ.jpg",
        "release_date": "2025-10-27",
        "title": "Alma Errante – Hibakusha",
        "video": false,
        "vote_average": 0.0,
        "vote_count": 0,
        "genre_ids_zh": [
            "纪录"
        ],
        "original_language_zh": "葡萄牙语"
    },
    {
        "adult": false,
        "backdrop_path": "/c8Iz9p3Llr9b3pQaZNBMRgKstCK.jpg",
        "genre_ids": [
            99
        ],
        "id": 1553631,
        "original_language": "nl",
        "original_title": "Vagevuur",
        "overview": "",
        "popularity": 0.072,
        "poster_path": null,
        "release_date": "2025-10-27",
        "title": "Vagevuur",
        "video": false,
        "vote_average": 0.0,
        "vote_count": 0,
        "genre_ids_zh": [
            "纪录"
        ],
        "original_language_zh": "荷兰语"
    },
    {
        "adult": false,
        "backdrop_path": "/c3ynEtCvdia05xKD4TgfOGCJS6y.jpg",
        "genre_ids": [
            35
        ],
        "id": 1549723,
        "original_language": "tr",
        "original_title": "En Güzel Cenaze Şarkıları",
        "overview": "",
        "popularity": 0.3762,
        "poster_path": "/svZPH5kozMfnnZYmrZ83wLJTA1n.jpg",
        "release_date": "2025-10-27",
        "title": "En Güzel Cenaze Şarkıları",
        "video": false,
        "vote_average": 0.0,
        "vote_count": 0,
        "genre_ids_zh": [
            "喜剧"
        ],
        "original_language_zh": "土耳其语"
    }
]