[
    {
        "adult": false,
        "backdrop_path": null,
        "genre_ids": [
            18,
            10749
        ],
        "id": 1358189,
        "original_language": "zh",
        "original_title": "永不失联的爱",
        "overview": "所谓宿命就是“最初是你，最后也依然是你”。经历人生巨变的林七七偶然救下林南一并彼此相爱，好友丁真见证了两人许多难忘的瞬间。当所有美好顺利展开，误会却让相爱的两个人走到分开的边缘。然而一场看似偶然的重逢，让两个人明白，我们可以错过任何人但唯独不能错过你，即使我们不小心走散，我也会拼命找到你。",
        "popularity": 0.3055,
        "poster_path": "/tKYgp7osnXuAr4KtOiowzjNxAM5.jpg",
        "release_date": "2025-05-20",
        "title": "永不失联的爱",
        "video": false,
        "vote_average": 0.0,
        "vote_count": 0,
        "genre_ids_zh": [
            "剧情",
            "爱情"
        ],
        "original_language_zh": "汉语"
    },
    {
        "adult": false,
        "backdrop_path": "/8luISMhhevU4ZzKbMAhlWO9GRTI.jpg",
        "genre_ids": [
            18
        ],
        "id": 1212271,
        "original_language": "en",
        "original_title": "Eleanor the Great",
        "overview": "",
        "popularity": 0.8614,
        "poster_path": "/n0YzvHT8791NEwQDGIAgO29jBDn.jpg",
        "release_date": "2025-05-20",
        "title": "Eleanor the Great",
        "video": false,
        "vote_average": 0.0,
        "vote_count": 0,
        "genre_ids_zh": [
            "剧情"
        ],
        "original_language_zh": "英语"
    },
    {
        "adult": false,
        "backdrop_path": "/szMgsSrRroRcT69hAC3wDaqEO5N.jpg",
        "genre_ids": [
            53,
            18
        ],
        "id": 1457374,
        "original_language": "en",
        "original_title": "Deadly Escape",
        "overview": "",
        "popularity": 0.2091,
        "poster_path": "/p5l8DwZN0agkazTowAvBhEKHXzT.jpg",
        "release_date": "2025-05-20",
        "title": "Deadly Escape",
        "video": false,
        "vote_average": 0.0,
        "vote_count": 0,
        "genre_ids_zh": [
            "惊悚",
            "剧情"
        ],
        "original_language_zh": "英语"
    },
    {
        "adult": false,
        "backdrop_path": "/8xTwDVY6rHutl2GFN5sJAnWGuHI.jpg",
        "genre_ids": [
            35
        ],
        "id": 1482648,
        "original_language": "en",
        "original_title": "The King: LIVE at the Avenue, June 1st, 2003",
        "overview": "",
        "popularity": 0.114,
        "poster_path": "/rVcej8k1QC4VCx5eHiDMNAsNctF.jpg",
        "release_date": "2025-05-20",
        "title": "The King: LIVE at the Avenue, June 1st, 2003",
        "video": false,
        "vote_average": 8.0,
        "vote_count": 1,
        "genre_ids_zh": [
            "喜剧"
        ],
        "original_language_zh": "英语"
    },
    {
        "adult": false,
        "backdrop_path": null,
        "genre_ids": [
            53
        ],
        "id": 1476802,
        "original_language": "en",
        "original_title": "Catharsis",
        "overview": "",
        "popularity": 0.0404,
        "poster_path": "/er38UHubO76aZB5bYdUzVVXMDAH.jpg",
        "release_date": "2025-05-20",
        "title": "Catharsis",
        "video": false,
        "vote_average": 0.0,
        "vote_count": 0,
        "genre_ids_zh": [
            "惊悚"
        ],
        "original_language_zh": "英语"
    },
    {
        "adult": false,
        "backdrop_path": "/4OuyqQGNHBj7I5bm4UXWBH2yUEJ.jpg",
        "genre_ids": [
            53
        ],
        "id": 1483057,
        "original_language": "en",
        "original_title": "Radio Karma",
        "overview": "",
        "popularity": 0.0286,
        "poster_path": "/8f2XBjwAEd51AxTgH7ygUXxiT4U.jpg",
        "release_date": "2025-05-20",
        "title": "Radio Karma",
        "video": false,
        "vote_average": 0.0,
        "vote_count": 0,
        "genre_ids_zh": [
            "惊悚"
        ],
        "original_language_zh": "英语"
    },
    {
        "adult": false,
        "backdrop_path": null,
        "genre_ids": [],
        "id": 1483827,
        "original_language": "en",
        "original_title": "and so we remembered",
        "overview": "",
        "popularity": 0.0071,
        "poster_path": "/pFH6wTehol35eWiX3nKytQpRHMH.jpg",
        "release_date": "2025-05-20",
        "title": "and so we remembered",
        "video": false,
        "vote_average": 0.0,
        "vote_count": 0,
        "genre_ids_zh": [],
        "original_language_zh": "英语"
    },
    {
        "adult": false,
        "backdrop_path": null,
        "genre_ids": [],
        "id": 1484022,
        "original_language": "en",
        "original_title": "nicolas cage pillow",
        "overview": "",
        "popularity": 0.0071,
        "poster_path": "/mSFd6mq6IzkMerYUqGbJuOpjhPq.jpg",
        "release_date": "2025-05-20",
        "title": "nicolas cage pillow",
        "video": false,
        "vote_average": 0.0,
        "vote_count": 0,
        "genre_ids_zh": [],
        "original_language_zh": "英语"
    },
    {
        "adult": false,
        "backdrop_path": null,
        "genre_ids": [
            80,
            18
        ],
        "id": 1483873,
        "original_language": "en",
        "original_title": "Goodfellas (Sweded)",
        "overview": "",
        "popularity": 0.1286,
        "poster_path": "/gM25efi3OgyoDlWTaC5Qh0lYyD4.jpg",
        "release_date": "2025-05-20",
        "title": "Goodfellas (Sweded)",
        "video": false,
        "vote_average": 0.0,
        "vote_count": 0,
        "genre_ids_zh": [
            "犯罪",
            "剧情"
        ],
        "original_language_zh": "英语"
    },
    {
        "adult": false,
        "backdrop_path": null,
        "genre_ids": [],
        "id": 1483834,
        "original_language": "en",
        "original_title": "Memoria",
        "overview": "",
        "popularity": 0.0071,
        "poster_path": "/uRSkF8yNRwKM9tLxGV7JO6Jb9Lc.jpg",
        "release_date": "2025-05-20",
        "title": "Memoria",
        "video": false,
        "vote_average": 0.0,
        "vote_count": 0,
        "genre_ids_zh": [],
        "original_language_zh": "英语"
    },
    {
        "adult": false,
        "backdrop_path": null,
        "genre_ids": [],
        "id": 1483833,
        "original_language": "en",
        "original_title": "Kolektibisyon: Locating the Artist Through a Collectivist Practice of Animation",
        "overview": "",
        "popularity": 0.0071,
        "poster_path": null,
        "release_date": "2025-05-20",
        "title": "Kolektibisyon: Locating the Artist Through a Collectivist Practice of Animation",
        "video": false,
        "vote_average": 0.0,
        "vote_count": 0,
        "genre_ids_zh": [],
        "original_language_zh": "英语"
    },
    {
        "adult": false,
        "backdrop_path": null,
        "genre_ids": [],
        "id": 1483828,
        "original_language": "en",
        "original_title": "Ang Luha ay Bahagi ng Karagatan",
        "overview": "",
        "popularity": 0.0071,
        "poster_path": "/rDkK8KkeXqyokBxBfeZzqPpz7Hk.jpg",
        "release_date": "2025-05-20",
        "title": "Ang Luha ay Bahagi ng Karagatan",
        "video": false,
        "vote_average": 0.0,
        "vote_count": 0,
        "genre_ids_zh": [],
        "original_language_zh": "英语"
    },
    {
        "adult": false,
        "backdrop_path": null,
        "genre_ids": [],
        "id": 1483822,
        "original_language": "en",
        "original_title": "A Tender Awakening",
        "overview": "",
        "popularity": 0.0071,
        "poster_path": "/qGQ42q3qY7m4B5CWXhRJwtvbejd.jpg",
        "release_date": "2025-05-20",
        "title": "A Tender Awakening",
        "video": false,
        "vote_average": 0.0,
        "vote_count": 0,
        "genre_ids_zh": [],
        "original_language_zh": "英语"
    },
    {
        "adult": false,
        "backdrop_path": null,
        "genre_ids": [],
        "id": 1483821,
        "original_language": "en",
        "original_title": "Playhouse",
        "overview": "",
        "popularity": 0.0071,
        "poster_path": "/8Eg1HTE9Zr89w6lkaPnsn8zby4I.jpg",
        "release_date": "2025-05-20",
        "title": "Playhouse",
        "video": false,
        "vote_average": 0.0,
        "vote_count": 0,
        "genre_ids_zh": [],
        "original_language_zh": "英语"
    },
    {
        "adult": false,
        "backdrop_path": null,
        "genre_ids": [],
        "id": 1483743,
        "original_language": "en",
        "original_title": "Up Here, Disappear",
        "overview": "",
        "popularity": 0.0071,
        "poster_path": "/geU5Dqgpubu4OZTJdl4wUKVh6Ms.jpg",
        "release_date": "2025-05-20",
        "title": "Up Here, Disappear",
        "video": false,
        "vote_average": 0.0,
        "vote_count": 0,
        "genre_ids_zh": [],
        "original_language_zh": "英语"
    },
    {
        "adult": false,
        "backdrop_path": null,
        "genre_ids": [],
        "id": 1483740,
        "original_language": "en",
        "original_title": "Super Diva",
        "overview": "",
        "popularity": 0.0071,
        "poster_path": "/48wUc0GsphyMp78ccBmyhBAWHG.jpg",
        "release_date": "2025-05-20",
        "title": "Super Diva",
        "video": false,
        "vote_average": 0.0,
        "vote_count": 0,
        "genre_ids_zh": [],
        "original_language_zh": "英语"
    },
    {
        "adult": false,
        "backdrop_path": null,
        "genre_ids": [],
        "id": 1483738,
        "original_language": "en",
        "original_title": "MAMAMO",
        "overview": "",
        "popularity": 0.0071,
        "poster_path": "/qlyb3udHsF0JyEHJgLlqbBDvx1n.jpg",
        "release_date": "2025-05-20",
        "title": "MAMAMO",
        "video": false,
        "vote_average": 0.0,
        "vote_count": 0,
        "genre_ids_zh": [],
        "original_language_zh": "英语"
    },
    {
        "adult": false,
        "backdrop_path": null,
        "genre_ids": [],
        "id": 1483737,
        "original_language": "en",
        "original_title": "Hindi Kukupas, Hindi Malalanta",
        "overview": "",
        "popularity": 0.0071,
        "poster_path": "/7rlm4yxbD5T9wfDiWku5Rzx3H0P.jpg",
        "release_date": "2025-05-20",
        "title": "Hindi Kukupas, Hindi Malalanta",
        "video": false,
        "vote_average": 0.0,
        "vote_count": 0,
        "genre_ids_zh": [],
        "original_language_zh": "英语"
    },
    {
        "adult": false,
        "backdrop_path": null,
        "genre_ids": [],
        "id": 1483723,
        "original_language": "en",
        "original_title": "Perslab",
        "overview": "",
        "popularity": 0.0071,
        "poster_path": "/lxSZBLQfx0uIkzrqoVk5kbM76QN.jpg",
        "release_date": "2025-05-20",
        "title": "Perslab",
        "video": false,
        "vote_average": 0.0,
        "vote_count": 0,
        "genre_ids_zh": [],
        "original_language_zh": "英语"
    },
    {
        "adult": false,
        "backdrop_path": null,
        "genre_ids": [],
        "id": 1483721,
        "original_language": "en",
        "original_title": "Lola's Choice Award!",
        "overview": "",
        "popularity": 0.0071,
        "poster_path": "/p5LEiWy3HgAVqaUH7X4hG8OoFKi.jpg",
        "release_date": "2025-05-20",
        "title": "Lola's Choice Award!",
        "video": false,
        "vote_average": 0.0,
        "vote_count": 0,
        "genre_ids_zh": [],
        "original_language_zh": "英语"
    },
    {
        "adult": false,
        "backdrop_path": null,
        "genre_ids": [],
        "id": 1483720,
        "original_language": "en",
        "original_title": "Monkey",
        "overview": "",
        "popularity": 0.0071,
        "poster_path": "/u4AoFv1549ScS5qqVFAoISvEmrp.jpg",
        "release_date": "2025-05-20",
        "title": "Monkey",
        "video": false,
        "vote_average": 0.0,
        "vote_count": 0,
        "genre_ids_zh": [],
        "original_language_zh": "英语"
    },
    {
        "adult": false,
        "backdrop_path": null,
        "genre_ids": [],
        "id": 1483719,
        "original_language": "en",
        "original_title": "Hands to Heaven",
        "overview": "",
        "popularity": 0.0,
        "poster_path": "/dKHVAKn1PEBnrkCtuY2zQTQ9e9A.jpg",
        "release_date": "2025-05-20",
        "title": "Hands to Heaven",
        "video": false,
        "vote_average": 0.0,
        "vote_count": 0,
        "genre_ids_zh": [],
        "original_language_zh": "英语"
    },
    {
        "adult": false,
        "backdrop_path": null,
        "genre_ids": [],
        "id": 1483715,
        "original_language": "en",
        "original_title": "Q.I.A.",
        "overview": "",
        "popularity": 0.0,
        "poster_path": "/CMPcRXpvr3ETxGn9ytoVnnAYfp.jpg",
        "release_date": "2025-05-20",
        "title": "Q.I.A.",
        "video": false,
        "vote_average": 0.0,
        "vote_count": 0,
        "genre_ids_zh": [],
        "original_language_zh": "英语"
    },
    {
        "adult": false,
        "backdrop_path": null,
        "genre_ids": [],
        "id": 1483713,
        "original_language": "en",
        "original_title": "TaTaTa",
        "overview": "",
        "popularity": 0.0,
        "poster_path": "/kqYAeCZn9uee6LJ6pjgXHfCYPVO.jpg",
        "release_date": "2025-05-20",
        "title": "TaTaTa",
        "video": false,
        "vote_average": 0.0,
        "vote_count": 0,
        "genre_ids_zh": [],
        "original_language_zh": "英语"
    },
    {
        "adult": false,
        "backdrop_path": null,
        "genre_ids": [],
        "id": 1483710,
        "original_language": "en",
        "original_title": "Doce de Pebrero",
        "overview": "",
        "popularity": 0.0,
        "poster_path": "/fE9tznoSZI4axDooY3zNa0hMyT6.jpg",
        "release_date": "2025-05-20",
        "title": "Doce de Pebrero",
        "video": false,
        "vote_average": 0.0,
        "vote_count": 0,
        "genre_ids_zh": [],
        "original_language_zh": "英语"
    },
    {
        "adult": false,
        "backdrop_path": null,
        "genre_ids": [],
        "id": 1483706,
        "original_language": "en",
        "original_title": "Sa Iyong Pagbalik",
        "overview": "",
        "popularity": 0.0,
        "poster_path": "/iu24edKUSgEifYDYtas71eKz2XH.jpg",
        "release_date": "2025-05-20",
        "title": "Sa Iyong Pagbalik",
        "video": false,
        "vote_average": 0.0,
        "vote_count": 0,
        "genre_ids_zh": [],
        "original_language_zh": "英语"
    },
    {
        "adult": false,
        "backdrop_path": null,
        "genre_ids": [],
        "id": 1483704,
        "original_language": "en",
        "original_title": "Digital Dreams",
        "overview": "",
        "popularity": 0.0,
        "poster_path": "/uqEXIzOUWZSoK8KbKyxA2L0SgkT.jpg",
        "release_date": "2025-05-20",
        "title": "Digital Dreams",
        "video": false,
        "vote_average": 0.0,
        "vote_count": 0,
        "genre_ids_zh": [],
        "original_language_zh": "英语"
    },
    {
        "adult": false,
        "backdrop_path": null,
        "genre_ids": [],
        "id": 1483702,
        "original_language": "en",
        "original_title": "Human?",
        "overview": "",
        "popularity": 0.0,
        "poster_path": "/xPHxh2N2RvD3Z5fxAmENGt7RaPn.jpg",
        "release_date": "2025-05-20",
        "title": "Human?",
        "video": false,
        "vote_average": 0.0,
        "vote_count": 0,
        "genre_ids_zh": [],
        "original_language_zh": "英语"
    },
    {
        "adult": false,
        "backdrop_path": null,
        "genre_ids": [],
        "id": 1483700,
        "original_language": "en",
        "original_title": "farther, closer, farther",
        "overview": "",
        "popularity": 0.0,
        "poster_path": "/vm6vGMyCT4bKw5wGiY0u3JqATvT.jpg",
        "release_date": "2025-05-20",
        "title": "farther, closer, farther",
        "video": false,
        "vote_average": 0.0,
        "vote_count": 0,
        "genre_ids_zh": [],
        "original_language_zh": "英语"
    },
    {
        "adult": false,
        "backdrop_path": null,
        "genre_ids": [],
        "id": 1483697,
        "original_language": "en",
        "original_title": "Ang Puting Sinulid",
        "overview": "",
        "popularity": 0.0,
        "poster_path": "/bCbkWSFiYNQNJND8BtQ7qn4PtRa.jpg",
        "release_date": "2025-05-20",
        "title": "Ang Puting Sinulid",
        "video": false,
        "vote_average": 0.0,
        "vote_count": 0,
        "genre_ids_zh": [],
        "original_language_zh": "英语"
    },
    {
        "adult": false,
        "backdrop_path": null,
        "genre_ids": [],
        "id": 1483695,
        "original_language": "en",
        "original_title": "Georgina",
        "overview": "",
        "popularity": 0.0,
        "poster_path": "/AdO4IRvcB6q1o8mE6WIEFgVcsUF.jpg",
        "release_date": "2025-05-20",
        "title": "Georgina",
        "video": false,
        "vote_average": 0.0,
        "vote_count": 0,
        "genre_ids_zh": [],
        "original_language_zh": "英语"
    },
    {
        "adult": false,
        "backdrop_path": null,
        "genre_ids": [],
        "id": 1483692,
        "original_language": "en",
        "original_title": "CALLING 84843",
        "overview": "",
        "popularity": 0.0,
        "poster_path": "/4EZE3DC1TUQ0dSndUpaJeR7a5eN.jpg",
        "release_date": "2025-05-20",
        "title": "CALLING 84843",
        "video": false,
        "vote_average": 0.0,
        "vote_count": 0,
        "genre_ids_zh": [],
        "original_language_zh": "英语"
    },
    {
        "adult": false,
        "backdrop_path": null,
        "genre_ids": [],
        "id": 1483690,
        "original_language": "en",
        "original_title": "Moonlighters",
        "overview": "",
        "popularity": 0.0,
        "poster_path": "/qUBoznkFrRUuGmyLXA57vrwaX1Y.jpg",
        "release_date": "2025-05-20",
        "title": "Moonlighters",
        "video": false,
        "vote_average": 0.0,
        "vote_count": 0,
        "genre_ids_zh": [],
        "original_language_zh": "英语"
    },
    {
        "adult": false,
        "backdrop_path": null,
        "genre_ids": [],
        "id": 1483687,
        "original_language": "en",
        "original_title": "Mga Aninong Dayo",
        "overview": "",
        "popularity": 0.0,
        "poster_path": "/tS5OmPUpq1j9tyI5q111rHPX8br.jpg",
        "release_date": "2025-05-20",
        "title": "Mga Aninong Dayo",
        "video": false,
        "vote_average": 0.0,
        "vote_count": 0,
        "genre_ids_zh": [],
        "original_language_zh": "英语"
    },
    {
        "adult": false,
        "backdrop_path": null,
        "genre_ids": [],
        "id": 1483686,
        "original_language": "en",
        "original_title": "good night, dad, i love you",
        "overview": "",
        "popularity": 0.0,
        "poster_path": "/2vWdRdfxv4cX8B9Sa4U5R9Sw3eX.jpg",
        "release_date": "2025-05-20",
        "title": "good night, dad, i love you",
        "video": false,
        "vote_average": 0.0,
        "vote_count": 0,
        "genre_ids_zh": [],
        "original_language_zh": "英语"
    },
    {
        "adult": false,
        "backdrop_path": null,
        "genre_ids": [],
        "id": 1483683,
        "original_language": "en",
        "original_title": "Mariposa",
        "overview": "",
        "popularity": 0.0,
        "poster_path": "/mZyzM5ljXYA52WE6F0HFwKzCbLy.jpg",
        "release_date": "2025-05-20",
        "title": "Mariposa",
        "video": false,
        "vote_average": 0.0,
        "vote_count": 0,
        "genre_ids_zh": [],
        "original_language_zh": "英语"
    },
    {
        "adult": false,
        "backdrop_path": null,
        "genre_ids": [],
        "id": 1483679,
        "original_language": "en",
        "original_title": "Present Tense",
        "overview": "",
        "popularity": 0.0,
        "poster_path": "/iFUIiMjAx1L3vvKVLeZkDWy91l2.jpg",
        "release_date": "2025-05-20",
        "title": "Present Tense",
        "video": false,
        "vote_average": 0.0,
        "vote_count": 0,
        "genre_ids_zh": [],
        "original_language_zh": "英语"
    },
    {
        "adult": false,
        "backdrop_path": null,
        "genre_ids": [],
        "id": 1483677,
        "original_language": "en",
        "original_title": "Remember Me Not",
        "overview": "",
        "popularity": 0.0,
        "poster_path": "/caKgqM7lYMbffpvsl85CipKfBdf.jpg",
        "release_date": "2025-05-20",
        "title": "Remember Me Not",
        "video": false,
        "vote_average": 0.0,
        "vote_count": 0,
        "genre_ids_zh": [],
        "original_language_zh": "英语"
    },
    {
        "adult": false,
        "backdrop_path": null,
        "genre_ids": [],
        "id": 1483676,
        "original_language": "en",
        "original_title": "Tumbang Preso",
        "overview": "",
        "popularity": 0.0,
        "poster_path": "/40mqnm4xTz1Yba5KdY78iuBFDUW.jpg",
        "release_date": "2025-05-20",
        "title": "Tumbang Preso",
        "video": false,
        "vote_average": 0.0,
        "vote_count": 0,
        "genre_ids_zh": [],
        "original_language_zh": "英语"
    },
    {
        "adult": false,
        "backdrop_path": "/wNpEnHxNQXSv2fc3bW0QNuswKs6.jpg",
        "genre_ids": [
            18,
            36
        ],
        "id": 1290450,
        "original_language": "fr",
        "original_title": "Love Me Tender",
        "overview": "",
        "popularity": 0.6296,
        "poster_path": "/wAOj7jNImqi76Dmm9tbf7BudBdu.jpg",
        "release_date": "2025-05-20",
        "title": "Love Me Tender",
        "video": false,
        "vote_average": 0.0,
        "vote_count": 0,
        "genre_ids_zh": [
            "剧情",
            "历史"
        ],
        "original_language_zh": "法语"
    },
    {
        "adult": false,
        "backdrop_path": "/kZ6omJ5fkHFJXxZTj6VllHadNkn.jpg",
        "genre_ids": [
            99
        ],
        "id": 1119539,
        "original_language": "fr",
        "original_title": "Imago",
        "overview": "",
        "popularity": 0.1468,
        "poster_path": "/eLkrbBYy294vLh2IETRTWU5FDIC.jpg",
        "release_date": "2025-05-20",
        "title": "Imago",
        "video": false,
        "vote_average": 0.0,
        "vote_count": 0,
        "genre_ids_zh": [
            "纪录"
        ],
        "original_language_zh": "法语"
    },
    {
        "adult": false,
        "backdrop_path": null,
        "genre_ids": [
            18
        ],
        "id": 1387837,
        "original_language": "fr",
        "original_title": "Dernier Road Trip",
        "overview": "",
        "popularity": 0.0362,
        "poster_path": "/hjJw5rD6eOvAj3qGV9xCDzz31U2.jpg",
        "release_date": "2025-05-20",
        "title": "Dernier Road Trip",
        "video": false,
        "vote_average": 0.0,
        "vote_count": 0,
        "genre_ids_zh": [
            "剧情"
        ],
        "original_language_zh": "法语"
    },
    {
        "adult": false,
        "backdrop_path": null,
        "genre_ids": [],
        "id": 1482613,
        "original_language": "fr",
        "original_title": "8mm, archives des Sagawa, montées",
        "overview": "",
        "popularity": 0.0143,
        "poster_path": null,
        "release_date": "2025-05-20",
        "title": "8mm, archives des Sagawa, montées",
        "video": false,
        "vote_average": 0.0,
        "vote_count": 0,
        "genre_ids_zh": [],
        "original_language_zh": "法语"
    },
    {
        "adult": false,
        "backdrop_path": null,
        "genre_ids": [
            14,
            878
        ],
        "id": 1484031,
        "original_language": "fr",
        "original_title": "R.E.M.",
        "overview": "",
        "popularity": 0.0,
        "poster_path": "/5WR68lplrHAclWuQPPTERd9Xc22.jpg",
        "release_date": "2025-05-20",
        "title": "R.E.M.",
        "video": false,
        "vote_average": 0.0,
        "vote_count": 0,
        "genre_ids_zh": [
            "奇幻",
            "科幻"
        ],
        "original_language_zh": "法语"
    },
    {
        "adult": false,
        "backdrop_path": null,
        "genre_ids": [
            35,
            80,
            28,
            10402
        ],
        "id": 1484013,
        "original_language": "fr",
        "original_title": "Koyaanisqatsi",
        "overview": "",
        "popularity": 0.0,
        "poster_path": "/iCuDUHxAvx8sPbcdE1bBic7xrL0.jpg",
        "release_date": "2025-05-20",
        "title": "Koyaanisqatsi",
        "video": false,
        "vote_average": 0.0,
        "vote_count": 0,
        "genre_ids_zh": [
            "喜剧",
            "犯罪",
            "动作",
            "音乐"
        ],
        "original_language_zh": "法语"
    },
    {
        "adult": false,
        "backdrop_path": null,
        "genre_ids": [],
        "id": 1480789,
        "original_language": "es",
        "original_title": "El Perro",
        "overview": "",
        "popularity": 0.0264,
        "poster_path": "/xYuZtDhgGFh1ioSG4Irn592LeNz.jpg",
        "release_date": "2025-05-20",
        "title": "El Perro",
        "video": false,
        "vote_average": 0.0,
        "vote_count": 0,
        "genre_ids_zh": [],
        "original_language_zh": "西班牙语"
    },
    {
        "adult": false,
        "backdrop_path": null,
        "genre_ids": [
            9648
        ],
        "id": 1473546,
        "original_language": "es",
        "original_title": "El Abismo de Camille",
        "overview": "",
        "popularity": 0.0286,
        "poster_path": "/3QUYq4SSdR98AKvRrmhwCRNIay.jpg",
        "release_date": "2025-05-20",
        "title": "El Abismo de Camille",
        "video": false,
        "vote_average": 0.0,
        "vote_count": 0,
        "genre_ids_zh": [
            "悬疑"
        ],
        "original_language_zh": "西班牙语"
    },
    {
        "adult": false,
        "backdrop_path": null,
        "genre_ids": [
            27,
            14,
            9648
        ],
        "id": 1258271,
        "original_language": "pt",
        "original_title": "Hysteria",
        "overview": "",
        "popularity": 0.093,
        "poster_path": "/fk5Z0cvoxcmJMvGsRt7jvsxaYne.jpg",
        "release_date": "2025-05-20",
        "title": "Hysteria",
        "video": false,
        "vote_average": 0.0,
        "vote_count": 0,
        "genre_ids_zh": [
            "恐怖",
            "奇幻",
            "悬疑"
        ],
        "original_language_zh": "葡萄牙语"
    },
    {
        "adult": false,
        "backdrop_path": null,
        "genre_ids": [
            99
        ],
        "id": 1467382,
        "original_language": "pt",
        "original_title": "De Borêta a Maria Bela",
        "overview": "",
        "popularity": 0.0594,
        "poster_path": "/3iZNQxv9aNXFg8n3qhzL7wp4CKs.jpg",
        "release_date": "2025-05-20",
        "title": "De Borêta a Maria Bela",
        "video": false,
        "vote_average": 0.0,
        "vote_count": 0,
        "genre_ids_zh": [
            "纪录"
        ],
        "original_language_zh": "葡萄牙语"
    },
    {
        "adult": false,
        "backdrop_path": "/yPcLfGaqFhVm4S0K8poRxknxEzR.jpg",
        "genre_ids": [
            14,
            18,
            10402
        ],
        "id": 1461116,
        "original_language": "pt",
        "original_title": "Samba Infinito",
        "overview": "",
        "popularity": 0.0482,
        "poster_path": "/gOwioQeeKrxFArJ3M1pAbDZtiVt.jpg",
        "release_date": "2025-05-20",
        "title": "Samba Infinito",
        "video": false,
        "vote_average": 0.0,
        "vote_count": 0,
        "genre_ids_zh": [
            "奇幻",
            "剧情",
            "音乐"
        ],
        "original_language_zh": "葡萄牙语"
    },
    {
        "adult": false,
        "backdrop_path": null,
        "genre_ids": [],
        "id": 1481646,
        "original_language": "pt",
        "original_title": "PERDÃO (ou \"O Sacrifício do Herói\")",
        "overview": "",
        "popularity": 0.0214,
        "poster_path": "/kHACkNsifeVHPvLnjYivtPqO9pG.jpg",
        "release_date": "2025-05-20",
        "title": "PERDÃO (ou \"O Sacrifício do Herói\")",
        "video": false,
        "vote_average": 0.0,
        "vote_count": 0,
        "genre_ids_zh": [],
        "original_language_zh": "葡萄牙语"
    },
    {
        "adult": false,
        "backdrop_path": null,
        "genre_ids": [
            9648,
            10752,
            878
        ],
        "id": 1416442,
        "original_language": "pt",
        "original_title": "TERRA AMEAÇADA 2",
        "overview": "",
        "popularity": 0.0214,
        "poster_path": null,
        "release_date": "2025-05-20",
        "title": "TERRA AMEAÇADA 2",
        "video": false,
        "vote_average": 0.0,
        "vote_count": 0,
        "genre_ids_zh": [
            "悬疑",
            "战争",
            "科幻"
        ],
        "original_language_zh": "葡萄牙语"
    },
    {
        "adult": false,
        "backdrop_path": "/nrWHOtrqQMwJnqrMNldo1sLtJQt.jpg",
        "genre_ids": [
            18,
            53
        ],
        "id": 1469180,
        "original_language": "it",
        "original_title": "Isola",
        "overview": "",
        "popularity": 0.0744,
        "poster_path": "/637zFwwBzTK9DWD5pxzvoxa4YJx.jpg",
        "release_date": "2025-05-20",
        "title": "Isola",
        "video": false,
        "vote_average": 0.0,
        "vote_count": 0,
        "genre_ids_zh": [
            "剧情",
            "惊悚"
        ],
        "original_language_zh": "意大利语"
    }
]