[
    {
        "adult": false,
        "backdrop_path": "/sxMQgCQg5JRFFq4wAd61tpytmt3.jpg",
        "genre_ids": [
            27
        ],
        "id": 1371850,
        "original_language": "en",
        "original_title": "Rock Springs",
        "overview": "",
        "popularity": 2.6013,
        "poster_path": "/oXK8FGCQ84fzlkzMINdPl3W5LVE.jpg",
        "release_date": "2026-01-25",
        "title": "Rock Springs",
        "video": false,
        "vote_average": 0.0,
        "vote_count": 0,
        "genre_ids_zh": [
            "恐怖"
        ],
        "original_language_zh": "英语"
    },
    {
        "adult": false,
        "backdrop_path": null,
        "genre_ids": [
            35
        ],
        "id": 1476682,
        "original_language": "en",
        "original_title": "Gail Daughtry and the Celebrity Sex Pass",
        "overview": "",
        "popularity": 0.6637,
        "poster_path": "/nmZtpHvLFq5aBKaziMmhpDGRSI8.jpg",
        "release_date": "2026-01-25",
        "title": "Gail Daughtry and the Celebrity Sex Pass",
        "video": false,
        "vote_average": 0.0,
        "vote_count": 0,
        "genre_ids_zh": [
            "喜剧"
        ],
        "original_language_zh": "英语"
    },
    {
        "adult": false,
        "backdrop_path": "/oWW84tYj52AtnB51lwnkCbOmSjJ.jpg",
        "genre_ids": [
            35,
            18
        ],
        "id": 1600761,
        "original_language": "en",
        "original_title": "The Worm",
        "overview": "",
        "popularity": 0.3614,
        "poster_path": "/mfMLjydOrM21LdPf9BDTGhJa9wA.jpg",
        "release_date": "2026-01-25",
        "title": "The Worm",
        "video": false,
        "vote_average": 0.0,
        "vote_count": 0,
        "genre_ids_zh": [
            "喜剧",
            "剧情"
        ],
        "original_language_zh": "英语"
    },
    {
        "adult": false,
        "backdrop_path": "/475EwwQP3Lg0kqhSC0xnZC4XBBd.jpg",
        "genre_ids": [
            35
        ],
        "id": 1579941,
        "original_language": "en",
        "original_title": "The Musical",
        "overview": "",
        "popularity": 0.3337,
        "poster_path": "/36pEPdTrYYP6SLeEJmfJpmO0Fs.jpg",
        "release_date": "2026-01-25",
        "title": "The Musical",
        "video": false,
        "vote_average": 0.0,
        "vote_count": 0,
        "genre_ids_zh": [
            "喜剧"
        ],
        "original_language_zh": "英语"
    },
    {
        "adult": false,
        "backdrop_path": "/rUYIfyUSJGw7og2Q5R0p50ZPCgz.jpg",
        "genre_ids": [
            18
        ],
        "id": 1482938,
        "original_language": "en",
        "original_title": "Union County",
        "overview": "",
        "popularity": 0.22,
        "poster_path": "/1qqOUFhE5DO12O2MFLdUIOlcxNT.jpg",
        "release_date": "2026-01-25",
        "title": "Union County",
        "video": false,
        "vote_average": 0.0,
        "vote_count": 0,
        "genre_ids_zh": [
            "剧情"
        ],
        "original_language_zh": "英语"
    },
    {
        "adult": false,
        "backdrop_path": null,
        "genre_ids": [
            99
        ],
        "id": 1591604,
        "original_language": "en",
        "original_title": "Soul Patrol",
        "overview": "",
        "popularity": 0.2004,
        "poster_path": "/oeNGDDT1GFQYaCtKyIwG8WTxYIE.jpg",
        "release_date": "2026-01-25",
        "title": "Soul Patrol",
        "video": false,
        "vote_average": 0.0,
        "vote_count": 0,
        "genre_ids_zh": [
            "纪录"
        ],
        "original_language_zh": "英语"
    },
    {
        "adult": false,
        "backdrop_path": "/bImnGjG8RFVMYIcpuIQBjfq7vjb.jpg",
        "genre_ids": [
            27
        ],
        "id": 1539177,
        "original_language": "en",
        "original_title": "Magenta House",
        "overview": "",
        "popularity": 0.1958,
        "poster_path": "/4g15BvHypzbboZafy58B80SYv1W.jpg",
        "release_date": "2026-01-25",
        "title": "Magenta House",
        "video": false,
        "vote_average": 0.0,
        "vote_count": 0,
        "genre_ids_zh": [
            "恐怖"
        ],
        "original_language_zh": "英语"
    },
    {
        "adult": false,
        "backdrop_path": null,
        "genre_ids": [
            99
        ],
        "id": 1299581,
        "original_language": "en",
        "original_title": "Knife: The Attempted Murder of Salman Rushdie",
        "overview": "",
        "popularity": 0.1547,
        "poster_path": "/tYivnHp9eHk6NQcQ9hmHWwGwhZ5.jpg",
        "release_date": "2026-01-25",
        "title": "Knife: The Attempted Murder of Salman Rushdie",
        "video": false,
        "vote_average": 0.0,
        "vote_count": 0,
        "genre_ids_zh": [
            "纪录"
        ],
        "original_language_zh": "英语"
    },
    {
        "adult": false,
        "backdrop_path": "/fBAj99OGL6UxuB0XEVxphwYr1Yl.jpg",
        "genre_ids": [],
        "id": 1596287,
        "original_language": "en",
        "original_title": "Frank & Louis",
        "overview": "",
        "popularity": 0.1521,
        "poster_path": "/6fV4cDuSBR3nkkBm7yL4LCNa5RQ.jpg",
        "release_date": "2026-01-25",
        "title": "Frank & Louis",
        "video": false,
        "vote_average": 0.0,
        "vote_count": 0,
        "genre_ids_zh": [],
        "original_language_zh": "英语"
    },
    {
        "adult": false,
        "backdrop_path": null,
        "genre_ids": [
            99
        ],
        "id": 1596300,
        "original_language": "en",
        "original_title": "Once Upon a Time in Harlem",
        "overview": "",
        "popularity": 0.143,
        "poster_path": "/xvPxmgQPm2a8Tai71TsQGDpQwKH.jpg",
        "release_date": "2026-01-25",
        "title": "Once Upon a Time in Harlem",
        "video": false,
        "vote_average": 0.0,
        "vote_count": 0,
        "genre_ids_zh": [
            "纪录"
        ],
        "original_language_zh": "英语"
    },
    {
        "adult": false,
        "backdrop_path": null,
        "genre_ids": [
            99
        ],
        "id": 1596266,
        "original_language": "en",
        "original_title": "Seized",
        "overview": "",
        "popularity": 0.1386,
        "poster_path": "/vsosbZd0A0iEg7YsjgCABxutQ2c.jpg",
        "release_date": "2026-01-25",
        "title": "Seized",
        "video": false,
        "vote_average": 0.0,
        "vote_count": 0,
        "genre_ids_zh": [
            "纪录"
        ],
        "original_language_zh": "英语"
    },
    {
        "adult": false,
        "backdrop_path": "/5MreFVYz1ROPKLu6KaWvWBlqeTT.jpg",
        "genre_ids": [
            99
        ],
        "id": 1596318,
        "original_language": "en",
        "original_title": "Cookie Queens",
        "overview": "",
        "popularity": 0.1257,
        "poster_path": "/a4g2oCkKlMJllC06nGIh7KaNock.jpg",
        "release_date": "2026-01-25",
        "title": "Cookie Queens",
        "video": false,
        "vote_average": 0.0,
        "vote_count": 0,
        "genre_ids_zh": [
            "纪录"
        ],
        "original_language_zh": "英语"
    },
    {
        "adult": false,
        "backdrop_path": null,
        "genre_ids": [],
        "id": 1619682,
        "original_language": "en",
        "original_title": "Arsenal VS Manchester United PL 25/26",
        "overview": "",
        "popularity": 0.1237,
        "poster_path": "/jPiGNraV13Xz71VMowmST8Kiou6.jpg",
        "release_date": "2026-01-25",
        "title": "Arsenal VS Manchester United PL 25/26",
        "video": false,
        "vote_average": 0.0,
        "vote_count": 0,
        "genre_ids_zh": [],
        "original_language_zh": "英语"
    },
    {
        "adult": false,
        "backdrop_path": "/m1FjaErKAVyy9euUyFH77XjbfV9.jpg",
        "genre_ids": [
            18
        ],
        "id": 1602689,
        "original_language": "en",
        "original_title": "Radiant Frost",
        "overview": "",
        "popularity": 0.1016,
        "poster_path": "/m2B93LIcKUi4oRizSaX1dXdDaDO.jpg",
        "release_date": "2026-01-25",
        "title": "Radiant Frost",
        "video": false,
        "vote_average": 0.0,
        "vote_count": 0,
        "genre_ids_zh": [
            "剧情"
        ],
        "original_language_zh": "英语"
    },
    {
        "adult": false,
        "backdrop_path": null,
        "genre_ids": [
            27
        ],
        "id": 1600609,
        "original_language": "en",
        "original_title": "Hypnagogia",
        "overview": "",
        "popularity": 0.0894,
        "poster_path": "/bkryDx4ZzThA846Rv6r0J2gZ8Bt.jpg",
        "release_date": "2026-01-25",
        "title": "Hypnagogia",
        "video": false,
        "vote_average": 0.0,
        "vote_count": 0,
        "genre_ids_zh": [
            "恐怖"
        ],
        "original_language_zh": "英语"
    },
    {
        "adult": false,
        "backdrop_path": null,
        "genre_ids": [],
        "id": 1619679,
        "original_language": "en",
        "original_title": "Crystal Palace VS Chelsea PL 25/26",
        "overview": "",
        "popularity": 0.0833,
        "poster_path": "/oavpkm0Wb2NMtFQHTjFrSCxRzjR.jpg",
        "release_date": "2026-01-25",
        "title": "Crystal Palace VS Chelsea PL 25/26",
        "video": false,
        "vote_average": 0.0,
        "vote_count": 0,
        "genre_ids_zh": [],
        "original_language_zh": "英语"
    },
    {
        "adult": false,
        "backdrop_path": null,
        "genre_ids": [
            99
        ],
        "id": 1595207,
        "original_language": "en",
        "original_title": "All About the Money",
        "overview": "",
        "popularity": 0.0803,
        "poster_path": "/9Cr9mXZ4nFZzibEX5V7zw3pho1z.jpg",
        "release_date": "2026-01-25",
        "title": "All About the Money",
        "video": false,
        "vote_average": 0.0,
        "vote_count": 0,
        "genre_ids_zh": [
            "纪录"
        ],
        "original_language_zh": "英语"
    },
    {
        "adult": false,
        "backdrop_path": "/6oWUvL2GwTcy9RjN0lvlQQ33x96.jpg",
        "genre_ids": [
            80
        ],
        "id": 1619193,
        "original_language": "en",
        "original_title": "Kevlar Soul",
        "overview": "",
        "popularity": 0.074,
        "poster_path": "/gGnNGlqz0y1qgfjcoP8vSDUp11o.jpg",
        "release_date": "2026-01-25",
        "title": "Kevlar Soul",
        "video": false,
        "vote_average": 0.0,
        "vote_count": 0,
        "genre_ids_zh": [
            "犯罪"
        ],
        "original_language_zh": "英语"
    },
    {
        "adult": false,
        "backdrop_path": null,
        "genre_ids": [
            35,
            878,
            18
        ],
        "id": 1511130,
        "original_language": "en",
        "original_title": "Past Life",
        "overview": "",
        "popularity": 0.0681,
        "poster_path": "/aIw0ummzRM4hph7nFp6hMIqn7eC.jpg",
        "release_date": "2026-01-25",
        "title": "Past Life",
        "video": false,
        "vote_average": 0.0,
        "vote_count": 0,
        "genre_ids_zh": [
            "喜剧",
            "科幻",
            "剧情"
        ],
        "original_language_zh": "英语"
    },
    {
        "adult": false,
        "backdrop_path": null,
        "genre_ids": [],
        "id": 1619680,
        "original_language": "en",
        "original_title": "Newcastle VS Aston Villa PL 25/26",
        "overview": "",
        "popularity": 0.0659,
        "poster_path": "/fOeCQGtStOkZcOo6fhxpcWkS5o7.jpg",
        "release_date": "2026-01-25",
        "title": "Newcastle VS Aston Villa PL 25/26",
        "video": false,
        "vote_average": 0.0,
        "vote_count": 0,
        "genre_ids_zh": [],
        "original_language_zh": "英语"
    },
    {
        "adult": false,
        "backdrop_path": null,
        "genre_ids": [],
        "id": 1619678,
        "original_language": "en",
        "original_title": "Brentford VS Nottingham Forest PL 25/26",
        "overview": "",
        "popularity": 0.0639,
        "poster_path": "/2PGcXzYf3BxzR87eQd1XwzKFSwp.jpg",
        "release_date": "2026-01-25",
        "title": "Brentford VS Nottingham Forest PL 25/26",
        "video": false,
        "vote_average": 0.0,
        "vote_count": 0,
        "genre_ids_zh": [],
        "original_language_zh": "英语"
    },
    {
        "adult": false,
        "backdrop_path": "/enMHynYxQaKe2l8tQuVFE85HNm2.jpg",
        "genre_ids": [
            35,
            18
        ],
        "id": 1595780,
        "original_language": "en",
        "original_title": "Crisis Actor",
        "overview": "",
        "popularity": 0.0584,
        "poster_path": "/g74kCDMqgJKuIgAjoBooHODabfg.jpg",
        "release_date": "2026-01-25",
        "title": "Crisis Actor",
        "video": false,
        "vote_average": 0.0,
        "vote_count": 0,
        "genre_ids_zh": [
            "喜剧",
            "剧情"
        ],
        "original_language_zh": "英语"
    },
    {
        "adult": false,
        "backdrop_path": "/q9Fy4NhikYmWBzTWA9v5S0U4S2y.jpg",
        "genre_ids": [
            53,
            27
        ],
        "id": 1614074,
        "original_language": "en",
        "original_title": "X125",
        "overview": "",
        "popularity": 0.0552,
        "poster_path": "/wI4trGv38zau1XmEQz51eQyQAeN.jpg",
        "release_date": "2026-01-25",
        "title": "X125",
        "video": false,
        "vote_average": 0.0,
        "vote_count": 0,
        "genre_ids_zh": [
            "惊悚",
            "恐怖"
        ],
        "original_language_zh": "英语"
    },
    {
        "adult": false,
        "backdrop_path": null,
        "genre_ids": [
            99
        ],
        "id": 1596306,
        "original_language": "en",
        "original_title": "Kikuyu Land",
        "overview": "",
        "popularity": 0.0525,
        "poster_path": "/a5YGraLDDgg6kTB5MxBzzrWjyWc.jpg",
        "release_date": "2026-01-25",
        "title": "Kikuyu Land",
        "video": false,
        "vote_average": 0.0,
        "vote_count": 0,
        "genre_ids_zh": [
            "纪录"
        ],
        "original_language_zh": "英语"
    },
    {
        "adult": false,
        "backdrop_path": null,
        "genre_ids": [
            35
        ],
        "id": 1609253,
        "original_language": "en",
        "original_title": "Shit Shower Shave",
        "overview": "",
        "popularity": 0.0379,
        "poster_path": "/5hbkZzJPfcL2acyXbFx0GPtGTUW.jpg",
        "release_date": "2026-01-25",
        "title": "Shit Shower Shave",
        "video": false,
        "vote_average": 0.0,
        "vote_count": 0,
        "genre_ids_zh": [
            "喜剧"
        ],
        "original_language_zh": "英语"
    },
    {
        "adult": false,
        "backdrop_path": null,
        "genre_ids": [
            16,
            27,
            14
        ],
        "id": 1616600,
        "original_language": "en",
        "original_title": "Trading Cards",
        "overview": "",
        "popularity": 0.0143,
        "poster_path": "/4RbyFHYrRwYzyb7cIVLvUIwikZQ.jpg",
        "release_date": "2026-01-25",
        "title": "Trading Cards",
        "video": false,
        "vote_average": 0.0,
        "vote_count": 0,
        "genre_ids_zh": [
            "动画",
            "恐怖",
            "奇幻"
        ],
        "original_language_zh": "英语"
    },
    {
        "adult": false,
        "backdrop_path": "/6wp3f1ooedFBtFQdA0Qy8mKY56F.jpg",
        "genre_ids": [
            18
        ],
        "id": 1559189,
        "original_language": "ja",
        "original_title": "炎上",
        "overview": "",
        "popularity": 2.0459,
        "poster_path": "/fCcI42Lj9nT3ntUqn4np6kJsuZt.jpg",
        "release_date": "2026-01-25",
        "title": "炎上",
        "video": false,
        "vote_average": 0.0,
        "vote_count": 0,
        "genre_ids_zh": [
            "剧情"
        ],
        "original_language_zh": "日语"
    },
    {
        "adult": false,
        "backdrop_path": "/n7SwzjjyuU9zYJBxxrqQEM022PF.jpg",
        "genre_ids": [
            878,
            14,
            28,
            12,
            18
        ],
        "id": 1594276,
        "original_language": "ja",
        "original_title": "仮面ライダーアインズ　ｗｉｔｈガールズリミックス",
        "overview": "",
        "popularity": 0.7902,
        "poster_path": "/3rUZJAmuOUDmVX5gbEdowVuzTHQ.jpg",
        "release_date": "2026-01-25",
        "title": "仮面ライダーアインズ　ｗｉｔｈガールズリミックス",
        "video": false,
        "vote_average": 0.0,
        "vote_count": 0,
        "genre_ids_zh": [
            "科幻",
            "奇幻",
            "动作",
            "冒险",
            "剧情"
        ],
        "original_language_zh": "日语"
    },
    {
        "adult": false,
        "backdrop_path": "/opiMqMisHcj8pwYNIEgbfHzsAB.jpg",
        "genre_ids": [
            28,
            18,
            35
        ],
        "id": 1618524,
        "original_language": "ja",
        "original_title": "「MISSION IN BATTLE ～新春絢爛～」",
        "overview": "",
        "popularity": 0.1177,
        "poster_path": "/3pOyKAkDU95f1Lh5iXpEdsJoWCU.jpg",
        "release_date": "2026-01-25",
        "title": "「MISSION IN BATTLE ～新春絢爛～」",
        "video": false,
        "vote_average": 0.0,
        "vote_count": 0,
        "genre_ids_zh": [
            "动作",
            "剧情",
            "喜剧"
        ],
        "original_language_zh": "日语"
    },
    {
        "adult": false,
        "backdrop_path": "/yMnLOsF7QmrBFhQ6y3CT29mj4r0.jpg",
        "genre_ids": [
            28,
            18
        ],
        "id": 1618518,
        "original_language": "ja",
        "original_title": "STARDOM 15th ANNIVERSARY STARDOM AWARD 2025 in TAKADANOBABA DAY2 〜試合〜",
        "overview": "",
        "popularity": 0.0915,
        "poster_path": "/8VdEOmYaSrioJNTE1JxeicnJQOi.jpg",
        "release_date": "2026-01-25",
        "title": "STARDOM 15th ANNIVERSARY STARDOM AWARD 2025 in TAKADANOBABA DAY2 〜試合〜",
        "video": false,
        "vote_average": 0.0,
        "vote_count": 0,
        "genre_ids_zh": [
            "动作",
            "剧情"
        ],
        "original_language_zh": "日语"
    },
    {
        "adult": false,
        "backdrop_path": "/e191hC5fG0eJAQ0kDzakq6tcemH.jpg",
        "genre_ids": [
            28,
            18,
            35,
            10402
        ],
        "id": 1620568,
        "original_language": "ja",
        "original_title": "TJPW The 6th \"Futari wa Princess\" Max Heart Tournament ~ Day 2",
        "overview": "",
        "popularity": 0.0311,
        "poster_path": null,
        "release_date": "2026-01-25",
        "title": "TJPW The 6th \"Futari wa Princess\" Max Heart Tournament ~ Day 2",
        "video": false,
        "vote_average": 0.0,
        "vote_count": 0,
        "genre_ids_zh": [
            "动作",
            "剧情",
            "喜剧",
            "音乐"
        ],
        "original_language_zh": "日语"
    },
    {
        "adult": false,
        "backdrop_path": "/sZtbgJ9KW5RvPwqQKnOwqkowuzi.jpg",
        "genre_ids": [
            99
        ],
        "id": 1487074,
        "original_language": "es",
        "original_title": "Jaripeo",
        "overview": "",
        "popularity": 0.153,
        "poster_path": "/qShLciBKeU5LIHNpJXz23yyBsul.jpg",
        "release_date": "2026-01-25",
        "title": "Jaripeo",
        "video": false,
        "vote_average": 0.0,
        "vote_count": 0,
        "genre_ids_zh": [
            "纪录"
        ],
        "original_language_zh": "西班牙语"
    },
    {
        "adult": false,
        "backdrop_path": null,
        "genre_ids": [
            18,
            10749
        ],
        "id": 1598955,
        "original_language": "es",
        "original_title": "Marga en el DF",
        "overview": "",
        "popularity": 0.1175,
        "poster_path": null,
        "release_date": "2026-01-25",
        "title": "Marga en el DF",
        "video": false,
        "vote_average": 0.0,
        "vote_count": 0,
        "genre_ids_zh": [
            "剧情",
            "爱情"
        ],
        "original_language_zh": "西班牙语"
    },
    {
        "adult": false,
        "backdrop_path": "/fX9SHegsmLuqg7DR7YxSDu68vs6.jpg",
        "genre_ids": [
            80,
            53
        ],
        "id": 1476374,
        "original_language": "pt",
        "original_title": "Todos os Homens da Magazine",
        "overview": "",
        "popularity": 0.1612,
        "poster_path": "/hu3zFFL6PoVsrgqHeyGSXW6xyuD.jpg",
        "release_date": "2026-01-25",
        "title": "Todos os Homens da Magazine",
        "video": false,
        "vote_average": 0.0,
        "vote_count": 0,
        "genre_ids_zh": [
            "犯罪",
            "惊悚"
        ],
        "original_language_zh": "葡萄牙语"
    },
    {
        "adult": false,
        "backdrop_path": "/qsMpwBzPLac6Awa6AGLqjbQN8VU.jpg",
        "genre_ids": [
            18
        ],
        "id": 1607652,
        "original_language": "pt",
        "original_title": "Dentro do meu peito mora um cão",
        "overview": "",
        "popularity": 0.1041,
        "poster_path": "/hOodPaefyEsWNqd0GS09t80mFCS.jpg",
        "release_date": "2026-01-25",
        "title": "Dentro do meu peito mora um cão",
        "video": false,
        "vote_average": 0.0,
        "vote_count": 0,
        "genre_ids_zh": [
            "剧情"
        ],
        "original_language_zh": "葡萄牙语"
    },
    {
        "adult": false,
        "backdrop_path": "/x6P3Ljq9gNLorpPVF8nzHgaisvO.jpg",
        "genre_ids": [
            18,
            36,
            10752
        ],
        "id": 1261188,
        "original_language": "sv",
        "original_title": "Den svenska länken",
        "overview": "",
        "popularity": 0.6407,
        "poster_path": "/cPUQx8mYKc0ms64DqHEUXNK7WRm.jpg",
        "release_date": "2026-01-25",
        "title": "Den svenska länken",
        "video": false,
        "vote_average": 0.0,
        "vote_count": 0,
        "genre_ids_zh": [
            "剧情",
            "历史",
            "战争"
        ],
        "original_language_zh": "瑞典语"
    },
    {
        "adult": false,
        "backdrop_path": null,
        "genre_ids": [],
        "id": 1613117,
        "original_language": "sv",
        "original_title": "Flatan",
        "overview": "",
        "popularity": 0.1049,
        "poster_path": null,
        "release_date": "2026-01-25",
        "title": "Flatan",
        "video": false,
        "vote_average": 0.0,
        "vote_count": 0,
        "genre_ids_zh": [],
        "original_language_zh": "瑞典语"
    },
    {
        "adult": false,
        "backdrop_path": null,
        "genre_ids": [
            99
        ],
        "id": 1613111,
        "original_language": "sv",
        "original_title": "August och kriget",
        "overview": "",
        "popularity": 0.1002,
        "poster_path": null,
        "release_date": "2026-01-25",
        "title": "August och kriget",
        "video": false,
        "vote_average": 0.0,
        "vote_count": 0,
        "genre_ids_zh": [
            "纪录"
        ],
        "original_language_zh": "瑞典语"
    },
    {
        "adult": false,
        "backdrop_path": null,
        "genre_ids": [
            18,
            10751
        ],
        "id": 1613109,
        "original_language": "sv",
        "original_title": "Syster min",
        "overview": "",
        "popularity": 0.0757,
        "poster_path": null,
        "release_date": "2026-01-25",
        "title": "Syster min",
        "video": false,
        "vote_average": 0.0,
        "vote_count": 0,
        "genre_ids_zh": [
            "剧情",
            "家庭"
        ],
        "original_language_zh": "瑞典语"
    },
    {
        "adult": false,
        "backdrop_path": "/fXFwJdhi84GcBbSPQXE7imN37zj.jpg",
        "genre_ids": [],
        "id": 1612058,
        "original_language": "sv",
        "original_title": "Nyheterna",
        "overview": "",
        "popularity": 0.0747,
        "poster_path": "/wo4vtU5bIxiJ8AdpxyoBiQ5EAWU.jpg",
        "release_date": "2026-01-25",
        "title": "Nyheterna",
        "video": false,
        "vote_average": 0.0,
        "vote_count": 0,
        "genre_ids_zh": [],
        "original_language_zh": "瑞典语"
    },
    {
        "adult": false,
        "backdrop_path": null,
        "genre_ids": [],
        "id": 1613116,
        "original_language": "sv",
        "original_title": "Ellen och Bengts hus",
        "overview": "",
        "popularity": 0.0363,
        "poster_path": null,
        "release_date": "2026-01-25",
        "title": "Ellen och Bengts hus",
        "video": false,
        "vote_average": 0.0,
        "vote_count": 0,
        "genre_ids_zh": [],
        "original_language_zh": "瑞典语"
    },
    {
        "adult": false,
        "backdrop_path": null,
        "genre_ids": [
            16,
            99
        ],
        "id": 1613119,
        "original_language": "sv",
        "original_title": "Det som finns kvar av mig",
        "overview": "",
        "popularity": 0.0143,
        "poster_path": null,
        "release_date": "2026-01-25",
        "title": "Det som finns kvar av mig",
        "video": false,
        "vote_average": 0.0,
        "vote_count": 0,
        "genre_ids_zh": [
            "动画",
            "纪录"
        ],
        "original_language_zh": "瑞典语"
    }
]