[
    {
        "adult": false,
        "backdrop_path": null,
        "genre_ids": [
            18,
            10765
        ],
        "id": 283777,
        "origin_country": [
            "中国"
        ],
        "original_language": "zh",
        "original_name": "花间一倾城",
        "overview": "来自“花都”平城的小种花匠顾青橙，因一只神秘萤火虫指引，在救治一朵白牡丹时吸入了其“花灵”，而此白牡丹竟是千年半妖吕耕云。 因父亲留下的遗言，顾青橙从小就立志救活9999朵花，等待百花仙君带她去天上见到想见的人。那夜，吕耕云于一朵巨大的白牡丹花中苏醒，此情此景让顾青橙坚定地认为他就是百花仙君，遂拜其为师。而吕耕云为了寻找取出花灵之法，查清父母当年冤案的真相，不得不伪装身份留在她的身边，伺机而动。而谁曾想顾青橙竟是谈虎色变的“采花大盗”… 二人在经历了一系列神奇的故事后，逐渐心意相通。但面对宿命的轮回，真的百花仙君的出现等，二人又不得不面临新的一轮选择与挑战。",
        "popularity": 0.067,
        "poster_path": "/gGbC5cS5rjpCXEEowVr88HjIej8.jpg",
        "first_air_date": "2025-02-27",
        "name": "花间一倾城",
        "vote_average": 0.0,
        "vote_count": 0,
        "genre_ids_zh": [
            "剧情",
            "科幻与奇幻"
        ],
        "original_language_zh": "汉语"
    },
    {
        "adult": false,
        "backdrop_path": "/dWSFwQCCHvSlIQGXt7YJh4kJLs0.jpg",
        "genre_ids": [
            18
        ],
        "id": 243881,
        "origin_country": [
            "美国"
        ],
        "original_language": "en",
        "original_name": "House of David",
        "overview": "《大卫王朝》讲述的是圣经人物大卫崛起并成为以色列最受欢迎的国王的故事。该系列为我们呈现了昔日强大的扫罗王因为骄傲自大而自取灭亡的全过程。在上帝的指引下，先知撒母耳膏立了一位出人意料的新王——一个离经叛道的少年。一个领袖的倒下势必会迎来另一个领袖的崛起。",
        "popularity": 11.711,
        "poster_path": "/o46T1xQUGGBZIqF7QN8YfW2MBha.jpg",
        "first_air_date": "2025-02-27",
        "name": "大卫王朝",
        "vote_average": 0.0,
        "vote_count": 0,
        "genre_ids_zh": [
            "剧情"
        ],
        "original_language_zh": "英语"
    },
    {
        "adult": false,
        "backdrop_path": "/pe4MCXUoTc1shQoqgU0LvPB3vjW.jpg",
        "genre_ids": [
            80
        ],
        "id": 251750,
        "origin_country": [
            "英国"
        ],
        "original_language": "en",
        "original_name": "Bergerac",
        "overview": "",
        "popularity": 11.206,
        "poster_path": "/gvha97ZZf0Z9NfmSov4UqHUb6kz.jpg",
        "first_air_date": "2025-02-27",
        "name": "Bergerac",
        "vote_average": 0.0,
        "vote_count": 0,
        "genre_ids_zh": [
            "犯罪"
        ],
        "original_language_zh": "英语"
    },
    {
        "adult": false,
        "backdrop_path": "/pp4jnkOneeb4FFcni9VUCyo18sZ.jpg",
        "genre_ids": [
            18
        ],
        "id": 232342,
        "origin_country": [
            "英国"
        ],
        "original_language": "en",
        "original_name": "Toxic Town",
        "overview": "",
        "popularity": 10.832,
        "poster_path": "/o1p8sTA6ZnFPoVscCxquiJusAYS.jpg",
        "first_air_date": "2025-02-27",
        "name": "Toxic Town",
        "vote_average": 9.0,
        "vote_count": 1,
        "genre_ids_zh": [
            "剧情"
        ],
        "original_language_zh": "英语"
    },
    {
        "adult": false,
        "backdrop_path": "/710XwLopmB8f1FCQoHYRS8agpKw.jpg",
        "genre_ids": [
            35,
            18
        ],
        "id": 241274,
        "origin_country": [
            "英国",
            "美国"
        ],
        "original_language": "en",
        "original_name": "Small Town, Big Story",
        "overview": "",
        "popularity": 10.815,
        "poster_path": "/nvMArio4918aYO2X4l2BlZg6oJf.jpg",
        "first_air_date": "2025-02-27",
        "name": "Small Town, Big Story",
        "vote_average": 0.0,
        "vote_count": 0,
        "genre_ids_zh": [
            "喜剧",
            "剧情"
        ],
        "original_language_zh": "英语"
    },
    {
        "adult": false,
        "backdrop_path": "/xY3RLTXgV0IHmyPAE97p3ePWY1R.jpg",
        "genre_ids": [
            35
        ],
        "id": 244623,
        "origin_country": [
            "美国"
        ],
        "original_language": "en",
        "original_name": "Running Point",
        "overview": "",
        "popularity": 10.783,
        "poster_path": "/xHpfi2dBdsgnFIx7DzfMd0DwTXo.jpg",
        "first_air_date": "2025-02-27",
        "name": "Running Point",
        "vote_average": 0.0,
        "vote_count": 0,
        "genre_ids_zh": [
            "喜剧"
        ],
        "original_language_zh": "英语"
    },
    {
        "adult": false,
        "backdrop_path": null,
        "genre_ids": [
            99
        ],
        "id": 281371,
        "origin_country": [
            "美国"
        ],
        "original_language": "en",
        "original_name": "Devil in the Family: The Fall of Ruby Franke",
        "overview": "",
        "popularity": 10.72,
        "poster_path": null,
        "first_air_date": "2025-02-27",
        "name": "Devil in the Family: The Fall of Ruby Franke",
        "vote_average": 0.0,
        "vote_count": 0,
        "genre_ids_zh": [
            "纪录"
        ],
        "original_language_zh": "英语"
    },
    {
        "adult": false,
        "backdrop_path": null,
        "genre_ids": [],
        "id": 284920,
        "origin_country": [
            "美国"
        ],
        "original_language": "en",
        "original_name": "Fabian Hernandez Gets Grounded",
        "overview": "",
        "popularity": 2.744,
        "poster_path": "/ibFlel6XcDaiQZvATeBzvNpXGUm.jpg",
        "first_air_date": "2025-02-27",
        "name": "Fabian Hernandez Gets Grounded",
        "vote_average": 0.0,
        "vote_count": 0,
        "genre_ids_zh": [],
        "original_language_zh": "英语"
    },
    {
        "adult": false,
        "backdrop_path": null,
        "genre_ids": [],
        "id": 283924,
        "origin_country": [
            "日本"
        ],
        "original_language": "ja",
        "original_name": "復讐カレシ～溺愛社長の顔にはウラがある～",
        "overview": "",
        "popularity": 10.667,
        "poster_path": "/mAhiHglFDHe05FpfPFUd9JM1JEZ.jpg",
        "first_air_date": "2025-02-27",
        "name": "復讐カレシ～溺愛社長の顔にはウラがある～",
        "vote_average": 0.0,
        "vote_count": 0,
        "genre_ids_zh": [],
        "original_language_zh": "日语"
    },
    {
        "adult": false,
        "backdrop_path": "/moJ8lgBeDMWHgDrPSmOvEH72HnA.jpg",
        "genre_ids": [
            18
        ],
        "id": 276257,
        "origin_country": [
            "韩国"
        ],
        "original_language": "ko",
        "original_name": "비밀 사이",
        "overview": "",
        "popularity": 10.699,
        "poster_path": "/kS6CGrxAFgFUCQyvubpFGDuxcGf.jpg",
        "first_air_date": "2025-02-27",
        "name": "비밀 사이",
        "vote_average": 0.0,
        "vote_count": 0,
        "genre_ids_zh": [
            "剧情"
        ],
        "original_language_zh": "韩语"
    },
    {
        "adult": false,
        "backdrop_path": null,
        "genre_ids": [
            10764,
            10767
        ],
        "id": 283645,
        "origin_country": [
            "韩国"
        ],
        "original_language": "ko",
        "original_name": "미친맛집: 미식가 친구의 맛집",
        "overview": "",
        "popularity": 10.661,
        "poster_path": null,
        "first_air_date": "2025-02-27",
        "name": "미친맛집: 미식가 친구의 맛집",
        "vote_average": 0.0,
        "vote_count": 0,
        "genre_ids_zh": [
            "真人秀",
            "脱口秀"
        ],
        "original_language_zh": "韩语"
    },
    {
        "adult": false,
        "backdrop_path": "/fHeifcsv6CphZXFOfBYLlMXk3kX.jpg",
        "genre_ids": [
            18,
            80,
            9648
        ],
        "id": 282792,
        "origin_country": [
            "泰国"
        ],
        "original_language": "th",
        "original_name": "ดาหลา บุปผา ฆาตกรรม",
        "overview": "",
        "popularity": 10.718,
        "poster_path": "/6J1LSnEFO5OPuztDzsdiWc3xJsT.jpg",
        "first_air_date": "2025-02-27",
        "name": "ดาหลา บุปผา ฆาตกรรม",
        "vote_average": 0.0,
        "vote_count": 0,
        "genre_ids_zh": [
            "剧情",
            "犯罪",
            "悬疑"
        ],
        "original_language_zh": "泰语"
    },
    {
        "adult": false,
        "backdrop_path": "/jqTBk6MAjYUtA21ipKJW1ImDsmG.jpg",
        "genre_ids": [
            18
        ],
        "id": 283270,
        "origin_country": [
            "法国"
        ],
        "original_language": "fr",
        "original_name": "Nismet",
        "overview": "",
        "popularity": 10.727,
        "poster_path": "/hPPBx2K3XK1jJb7llUWytPJDkkK.jpg",
        "first_air_date": "2025-02-27",
        "name": "Nismet",
        "vote_average": 0.0,
        "vote_count": 0,
        "genre_ids_zh": [
            "剧情"
        ],
        "original_language_zh": "法语"
    },
    {
        "adult": false,
        "backdrop_path": "/gzNKeXtIOrv6mxBgw0Sh4plo8Ud.jpg",
        "genre_ids": [
            35
        ],
        "id": 246929,
        "origin_country": [
            "西班牙"
        ],
        "original_language": "es",
        "original_name": "Su majestad",
        "overview": "",
        "popularity": 11.298,
        "poster_path": "/oYz66iyll5q5yImMnzVkvUOxBho.jpg",
        "first_air_date": "2025-02-27",
        "name": "Su majestad",
        "vote_average": 0.0,
        "vote_count": 0,
        "genre_ids_zh": [
            "喜剧"
        ],
        "original_language_zh": "西班牙语"
    },
    {
        "adult": false,
        "backdrop_path": "/iJx6Aem99sjMBH4jC51ELN4QA1h.jpg",
        "genre_ids": [
            18,
            10759
        ],
        "id": 280043,
        "origin_country": [
            "墨西哥"
        ],
        "original_language": "es",
        "original_name": "Cóyotl, héroe y bestia",
        "overview": "",
        "popularity": 10.748,
        "poster_path": "/1ILKt1kZgCuDjEXjeVueqsgIxdV.jpg",
        "first_air_date": "2025-02-27",
        "name": "Cóyotl, héroe y bestia",
        "vote_average": 0.0,
        "vote_count": 0,
        "genre_ids_zh": [
            "剧情",
            "动作与冒险"
        ],
        "original_language_zh": "西班牙语"
    },
    {
        "adult": false,
        "backdrop_path": null,
        "genre_ids": [
            10764,
            99
        ],
        "id": 282362,
        "origin_country": [
            "荷兰"
        ],
        "original_language": "nl",
        "original_name": "Bizarre Erfenissen",
        "overview": "",
        "popularity": 10.709,
        "poster_path": null,
        "first_air_date": "2025-02-27",
        "name": "Bizarre Erfenissen",
        "vote_average": 0.0,
        "vote_count": 0,
        "genre_ids_zh": [
            "真人秀",
            "纪录"
        ],
        "original_language_zh": "荷兰语"
    },
    {
        "adult": false,
        "backdrop_path": "/iIRbSINMALnop0EMu7o9mPSmil7.jpg",
        "genre_ids": [
            10764
        ],
        "id": 284675,
        "origin_country": [
            "挪威"
        ],
        "original_language": "no",
        "original_name": "kan vi hjelpe til?",
        "overview": "",
        "popularity": 10.657,
        "poster_path": "/mileN0qxVGBmuWEngLl1SM4giUT.jpg",
        "first_air_date": "2025-02-27",
        "name": "kan vi hjelpe til?",
        "vote_average": 0.0,
        "vote_count": 0,
        "genre_ids_zh": [
            "真人秀"
        ],
        "original_language_zh": "挪威语"
    }
]